krtools/__init__.py
krtools/__main__.py
krtools/conf.py
krtools/sqltools/__init__.py
krtools/sqltools/__main__.py
krtools/sqltools/build.py
krtools/sqltools/create.py
krtools-0.1.0.dist-info/METADATA
krtools-0.1.0.dist-info/entry_points.txt
krtools-0.1.0.dist-info/WHEEL
krtools-0.1.0.dist-info/LICENSE
krtools-0.1.0.dist-info/RECORD
